pydantic_dict/__init__.py
pydantic_dict/mixins/__init__.py
pydantic_dict/mixins/dict_encoders.py
pydantic_dict_encoders-0.2.dist-info/LICENSE
pydantic_dict_encoders-0.2.dist-info/WHEEL
pydantic_dict_encoders-0.2.dist-info/METADATA
pydantic_dict_encoders-0.2.dist-info/RECORD
