Metadata-Version: 2.1
Name: pydantic-dict-encoders
Version: 0.2
Summary: Pydantic mixins for support custom encoding dict
Home-page: https://github.com/i8enn/pydantic_dict_encoders
License: MIT
Keywords: pydantic,dict,encoders,json
Author: Ivan Galin
Author-email: i.galin@devartsteam.ru
Maintainer: Ivan Galin
Maintainer-email: i.galin@devartsteam.ru
Requires-Python: >=3.7,<4.0
Classifier: Development Status :: 4 - Beta
Classifier: Environment :: Console
Classifier: Environment :: MacOS X
Classifier: Framework :: Pydantic
Classifier: Intended Audience :: Developers
Classifier: Intended Audience :: Information Technology
Classifier: Intended Audience :: System Administrators
Classifier: License :: OSI Approved :: MIT License
Classifier: Operating System :: POSIX :: Linux
Classifier: Operating System :: Unix
Classifier: Programming Language :: Python
Classifier: Programming Language :: Python :: 3
Classifier: Programming Language :: Python :: 3.7
Classifier: Programming Language :: Python :: 3.8
Classifier: Programming Language :: Python :: 3.9
Classifier: Programming Language :: Python :: 3.10
Classifier: Programming Language :: Python :: 3.11
Classifier: Programming Language :: Python :: 3 :: Only
Classifier: Programming Language :: Python :: Implementation :: CPython
Classifier: Topic :: Internet
Classifier: Topic :: Software Development :: Libraries :: Python Modules
Requires-Dist: pydantic (>=1.0.0,<2.0.0)
Project-URL: Documentation, https://github.com/i8enn/pydantic_dict_encoders
Project-URL: Repository, https://github.com/i8enn/pydantic_dict_encoders
